labs/Lab2-SigGen/task3/counter.sv
module counter #(
    parameter WIDTH = 9
)(
    //interface signals
    input logic clk,
    input logic rst,
    input logic en,
    input logic [WIDTH-1:0] incr,
    output logic [WIDTH-1:0] count
);

always_ff @ (posedge clk) begin
    
    if (rst) 
        count <= {WIDTH{1'b0}};
    else if (en)           
        count <= count + incr;
        
end

endmodule

labs/Lab2-SigGen/task3/ram.sv
module ram #(
    parameter ADDRESS_WIDTH = 9,
    parameter DATA_WIDTH = 8
)(
    input logic                         clk,
    input logic                         wr_en,
    input logic                         rd_en,
    input logic [ADDRESS_WIDTH-1:0]     wr_addr,
    input logic [ADDRESS_WIDTH-1:0]     rd_addr,
    input logic [DATA_WIDTH-1:0]        din,
    output logic [DATA_WIDTH-1:0]       dout
);

logic [DATA_WIDTH-1:0] ram_array [2**ADDRESS_WIDTH-1:0];

always_ff @(posedge clk) begin
    if (wr_en == 1'b1)
        ram_array[wr_addr] <= din;
    if (rd_en == 1'b1)
        // output is synchronous
        dout <= ram_array[rd_addr];
end
endmodule

labs/Lab2-SigGen/task3/sigdelay.sv
module sigdelay #(
    parameter ADDRESS_WIDTH = 9,
    parameter DATA_WIDTH = 8
) (
    input logic clk,
    input logic rst,
    input logic en,
    input logic rd_en,
    input logic wr_en,
    input logic incr,
    input logic [ADDRESS_WIDTH-1:0] offset,
    input logic [DATA_WIDTH-1:0] din,
    output logic [DATA_WIDTH-1:0] dout
);

logic [ADDRESS_WIDTH-1:0] count;
logic [ADDRESS_WIDTH-1:0] rd_addr;
logic [ADDRESS_WIDTH-1:0] wr_addr;

assign wr_addr = count;
assign rd_addr = count + offset;

ram #(
    .ADDRESS_WIDTH(ADDRESS_WIDTH),
    .DATA_WIDTH(DATA_WIDTH)
) ram1 (
    .clk(clk),
    .wr_en(wr_en),
    .rd_en(rd_en),
    .wr_addr(wr_addr),
    .rd_addr(rd_addr),
    .din(din),
    .dout(dout)
);

counter #(
    .WIDTH(ADDRESS_WIDTH)
) counter1 (
    .clk(clk),
    .rst(rst),
    .en(en),
    .incr(incr),
    .count(count)
);

endmodule

labs/Lab2-SigGen/task3/sigdelay.vcd
$version Generated by VerilatedVcd $end
$date Tue Nov  4 10:27:29 2025 $end
$timescale 1ps $end

 $scope module TOP $end
  $var wire  1 # clk $end
  $var wire  8 * din [7:0] $end
  $var wire  8 + dout [7:0] $end
  $var wire  1 % en $end
  $var wire  1 ( incr $end
  $var wire  9 ) offset [8:0] $end
  $var wire  1 & rd_en $end
  $var wire  1 $ rst $end
  $var wire  1 ' wr_en $end
  $scope module sigdelay $end
   $var wire 32 / ADDRESS_WIDTH [31:0] $end
   $var wire 32 0 DATA_WIDTH [31:0] $end
   $var wire  1 # clk $end
   $var wire  9 , count [8:0] $end
   $var wire  8 * din [7:0] $end
   $var wire  8 + dout [7:0] $end
   $var wire  1 % en $end
   $var wire  1 ( incr $end
   $var wire  9 ) offset [8:0] $end
   $var wire  9 - rd_addr [8:0] $end
   $var wire  1 & rd_en $end
   $var wire  1 $ rst $end
   $var wire  9 , wr_addr [8:0] $end
   $var wire  1 ' wr_en $end
   $scope module counter1 $end
    $var wire 32 / WIDTH [31:0] $end
    $var wire  1 # clk $end
    $var wire  9 , count [8:0] $end
    $var wire  1 % en $end
    $var wire  9 . incr [8:0] $end
    $var wire  1 $ rst $end
   $upscope $end
   $scope module ram1 $end
    $var wire 32 / ADDRESS_WIDTH [31:0] $end
    $var wire 32 0 DATA_WIDTH [31:0] $end
    $var wire  1 # clk $end
    $var wire  8 * din [7:0] $end
    $var wire  8 + dout [7:0] $end
    $var wire  9 - rd_addr [8:0] $end
    $var wire  1 & rd_en $end
    $var wire  9 , wr_addr [8:0] $end
    $var wire  1 ' wr_en $end
   $upscope $end
  $upscope $end
 $upscope $end
$enddefinitions $end


#0
1#
1$
1%
1&
1'
1(
b001000000 )
b00000000 *
b00000000 +
b000000000 ,
b001000000 -
b000000001 .
b00000000000000000000000000001001 /
b00000000000000000000000000001000 0
#1
0#
#2
1#
b001001000 )
b01101101 *
b001001000 -
#3
0#
#4
1#
0$
b01110001 *
#5
0#
#6
1#
b01110011 *
b000000001 ,
b001001001 -
#7
0#
#8
1#
b01110010 *
b000000010 ,
b001001010 -
#9
0#
#10
1#
b01101111 *
b000000011 ,
b001001011 -
#11
0#
#12
1#
b01110001 *
b000000100 ,
b001001100 -
#13
0#
#14
1#
b01110011 *
b000000101 ,
b001001101 -
#15
0#
#16
1#
b01110001 *
b000000110 ,
b001001110 -
#17
0#
#18
1#
b01110011 *
b000000111 ,
b001001111 -
#19
0#
#20
1#
b01110010 *
b000001000 ,
b001010000 -
#21
0#
#22
1#
b01110011 *
b000001001 ,
b001010001 -
#23
0#
#24
1#
b01110001 *
b000001010 ,
b001010010 -
#25
0#
#26
1#
b01110010 *
b000001011 ,
b001010011 -
#27
0#
#28
1#
b01110001 *
b000001100 ,
b001010100 -
#29
0#
#30
1#
b01110011 *
b000001101 ,
b001010101 -
#31
0#
#32
1#
b000001110 ,
b001010110 -
#33
0#
#34
1#
b01110010 *
b000001111 ,
b001010111 -
#35
0#
#36
1#
b01110101 *
b000010000 ,
b001011000 -
#37
0#
#38
1#
b01110010 *
b000010001 ,
b001011001 -
#39
0#
#40
1#
b01110101 *
b000010010 ,
b001011010 -
#41
0#
#42
1#
b01110010 *
b000010011 ,
b001011011 -
#43
0#
#44
1#
b01110000 *
b000010100 ,
b001011100 -
#45
0#
#46
1#
b01110010 *
b000010101 ,
b001011101 -
#47
0#
#48
1#
b01110000 *
b000010110 ,
b001011110 -
#49
0#
#50
1#
b01110001 *
b000010111 ,
b001011111 -
#51
0#
#52
1#
b01110010 *
b000011000 ,
b001100000 -
#53
0#
#54
1#
b01101111 *
b000011001 ,
b001100001 -
#55
0#
#56
1#
b01110001 *
b000011010 ,
b001100010 -
#57
0#
#58
1#
b000011011 ,
b001100011 -
#59
0#
#60
1#
b000011100 ,
b001100100 -
#61
0#
#62
1#
b01101110 *
b000011101 ,
b001100101 -
#63
0#
#64
1#
b01110001 *
b000011110 ,
b001100110 -
#65
0#
#66
1#
b000011111 ,
b001100111 -
#67
0#
#68
1#
b000100000 ,
b001101000 -
#69
0#
#70
1#
b01110000 *
b000100001 ,
b001101001 -
#71
0#
#72
1#
b01101100 *
b000100010 ,
b001101010 -
#73
0#
#74
1#
b01101110 *
b000100011 ,
b001101011 -
#75
0#
#76
1#
b000100100 ,
b001101100 -
#77
0#
#78
1#
b01110000 *
b000100101 ,
b001101101 -
#79
0#
#80
1#
b01101101 *
b000100110 ,
b001101110 -
#81
0#
#82
1#
b01101110 *
b000100111 ,
b001101111 -
#83
0#
#84
1#
b000101000 ,
b001110000 -
#85
0#
#86
1#
b01101100 *
b000101001 ,
b001110001 -
#87
0#
#88
1#
b01101010 *
b000101010 ,
b001110010 -
#89
0#
#90
1#
b01101001 *
b000101011 ,
b001110011 -
#91
0#
#92
1#
b01101101 *
b000101100 ,
b001110100 -
#93
0#
#94
1#
b01101100 *
b000101101 ,
b001110101 -
#95
0#
#96
1#
b01101101 *
b000101110 ,
b001110110 -
#97
0#
#98
1#
b01101111 *
b000101111 ,
b001110111 -
#99
0#
#100
1#
b000110000 ,
b001111000 -
#101
0#
#102
1#
b000110001 ,
b001111001 -
#103
0#
#104
1#
b01110010 *
b000110010 ,
b001111010 -
#105
0#
#106
1#
b01110000 *
b000110011 ,
b001111011 -
#107
0#
#108
1#
b01101101 *
b000110100 ,
b001111100 -
#109
0#
#110
1#
b01101110 *
b000110101 ,
b001111101 -
#111
0#
#112
1#
b01101111 *
b000110110 ,
b001111110 -
#113
0#
#114
1#
b000110111 ,
b001111111 -
#115
0#
#116
1#
b000111000 ,
b010000000 -
#117
0#
#118
1#
b01110000 *
b000111001 ,
b010000001 -
#119
0#
#120
1#
b000111010 ,
b010000010 -
#121
0#
#122
1#
b01110010 *
b000111011 ,
b010000011 -
#123
0#
#124
1#
b01110011 *
b000111100 ,
b010000100 -
#125
0#
#126
1#
b01110100 *
b000111101 ,
b010000101 -
#127
0#
#128
1#
b000111110 ,
b010000110 -
#129
0#
#130
1#
b01111000 *
b000111111 ,
b010000111 -
#131
0#
#132
1#
b01110010 *
b001000000 ,
b010001000 -
#133
0#
#134
1#
b01110011 *
b001000001 ,
b010001001 -
#135
0#
#136
1#
b01110010 *
b001000010 ,
b010001010 -
#137
0#
#138
1#
b01110011 *
b001000011 ,
b010001011 -
#139
0#
#140
1#
b001000100 ,
b010001100 -
#141
0#
#142
1#
b001000101 ,
b010001101 -
#143
0#
#144
1#
b01110110 *
b001000110 ,
b010001110 -
#145
0#
#146
1#
b01110010 *
b001000111 ,
b010001111 -
#147
0#
#148
1#
b01110001 *
b001001000 ,
b010010000 -
#149
0#
#150
1#
b01110010 *
b001001001 ,
b010010001 -
#151
0#
#152
1#
b01110000 *
b001001010 ,
b010010010 -
#153
0#
#154
1#
b01110010 *
b001001011 ,
b010010011 -
#155
0#
#156
1#
b01101111 *
b001001100 ,
b010010100 -
#157
0#
#158
1#
b001001101 ,
b010010101 -
#159
0#
#160
1#
b01101110 *
b001001110 ,
b010010110 -
#161
0#
#162
1#
b01101101 *
b001001111 ,
b010010111 -
#163
0#
#164
1#
b001010000 ,
b010011000 -
#165
0#
#166
1#
b01101110 *
b001010001 ,
b010011001 -
#167
0#
#168
1#
b01101100 *
b001010010 ,
b010011010 -
#169
0#
#170
1#
b01101101 *
b001010011 ,
b010011011 -
#171
0#
#172
1#
b01101010 *
b001010100 ,
b010011100 -
#173
0#
#174
1#
b01101001 *
b001010101 ,
b010011101 -
#175
0#
#176
1#
b01101111 *
b001010110 ,
b010011110 -
#177
0#
#178
1#
b01101101 *
b001010111 ,
b010011111 -
#179
0#
#180
1#
b01101111 *
b001011000 ,
b010100000 -
#181
0#
#182
1#
b01110001 *
b001011001 ,
b010100001 -
#183
0#
#184
1#
b01101110 *
b001011010 ,
b010100010 -
#185
0#
#186
1#
b01101100 *
b001011011 ,
b010100011 -
#187
0#
#188
1#
b01101101 *
b001011100 ,
b010100100 -
#189
0#
#190
1#
b01101100 *
b001011101 ,
b010100101 -
#191
0#
#192
1#
b01101111 *
b001011110 ,
b010100110 -
#193
0#
#194
1#
b01101110 *
b001011111 ,
b010100111 -
#195
0#
#196
1#
b001100000 ,
b010101000 -
#197
0#
#198
1#
b001100001 ,
b010101001 -
#199
0#
#200
1#
b001100010 ,
b010101010 -
#201
0#
#202
1#
b01101111 *
b001100011 ,
b010101011 -
#203
0#
#204
1#
b01101101 *
b001100100 ,
b010101100 -
#205
0#
#206
1#
b001100101 ,
b010101101 -
#207
0#
#208
1#
b01101100 *
b001100110 ,
b010101110 -
#209
0#
#210
1#
b01101010 *
b001100111 ,
b010101111 -
#211
0#
#212
1#
b01101101 *
b001101000 ,
b010110000 -
#213
0#
#214
1#
b01101100 *
b001101001 ,
b010110001 -
#215
0#
#216
1#
b01101101 *
b001101010 ,
b010110010 -
#217
0#
#218
1#
b01101100 *
b001101011 ,
b010110011 -
#219
0#
#220
1#
b01101110 *
b001101100 ,
b010110100 -
#221
0#
#222
1#
b01101100 *
b001101101 ,
b010110101 -
#223
0#
#224
1#
b01101011 *
b001101110 ,
b010110110 -
#225
0#
#226
1#
b01101100 *
b001101111 ,
b010110111 -
#227
0#
#228
1#
b01101101 *
b001110000 ,
b010111000 -
#229
0#
#230
1#
b01101100 *
b001110001 ,
b010111001 -
#231
0#
#232
1#
b01101011 *
b001110010 ,
b010111010 -
#233
0#
#234
1#
b01110000 *
b001110011 ,
b010111011 -
#235
0#
#236
1#
b01101110 *
b001110100 ,
b010111100 -
#237
0#
#238
1#
b01101100 *
b001110101 ,
b010111101 -
#239
0#
#240
1#
b01101111 *
b001110110 ,
b010111110 -
#241
0#
#242
1#
b01101101 *
b001110111 ,
b010111111 -
#243
0#
#244
1#
b01101100 *
b001111000 ,
b011000000 -
#245
0#
#246
1#
b01110000 *
b001111001 ,
b011000001 -
#247
0#
#248
1#
b01101110 *
b001111010 ,
b011000010 -
#249
0#
#250
1#
b01101111 *
b001111011 ,
b011000011 -
#251
0#
#252
1#
b001111100 ,
b011000100 -
#253
0#
#254
1#
b01101101 *
b001111101 ,
b011000101 -
#255
0#
#256
1#
b01101111 *
b001111110 ,
b011000110 -
#257
0#
#258
1#
b01101110 *
b001111111 ,
b011000111 -
#259
0#
#260
1#
b01101100 *
b010000000 ,
b011001000 -
#261
0#
#262
1#
b01110000 *
b010000001 ,
b011001001 -
#263
0#
#264
1#
b010000010 ,
b011001010 -
#265
0#
#266
1#
b01101101 *
b010000011 ,
b011001011 -
#267
0#
#268
1#
b01110010 *
b010000100 ,
b011001100 -
#269
0#
#270
1#
b01110001 *
b010000101 ,
b011001101 -
#271
0#
#272
1#
b01101110 *
b010000110 ,
b011001110 -
#273
0#
#274
1#
b010000111 ,
b011001111 -
#275
0#
#276
1#
b010001000 ,
b011010000 -
#277
0#
#278
1#
b01101100 *
b010001001 ,
b011010001 -
#279
0#
#280
1#
b01110000 *
b010001010 ,
b011010010 -
#281
0#
#282
1#
b01101111 *
b010001011 ,
b011010011 -
#283
0#
#284
1#
b01101110 *
b010001100 ,
b011010100 -
#285
0#
#286
1#
b01101111 *
b010001101 ,
b011010101 -
#287
0#
#288
1#
b010001110 ,
b011010110 -
#289
0#
#290
1#
b01110010 *
b010001111 ,
b011010111 -
#291
0#
#292
1#
b01101111 *
b010010000 ,
b011011000 -
#293
0#
#294
1#
b010010001 ,
b011011001 -
#295
0#
#296
1#
b01110000 *
b010010010 ,
b011011010 -
#297
0#
#298
1#
b010010011 ,
b011011011 -
#299
0#
#300
1#
b01101111 *
b010010100 ,
b011011100 -
#301
0#
#302
1#
b01110010 *
b010010101 ,
b011011101 -
#303
0#
#304
1#
b01101111 *
b010010110 ,
b011011110 -
#305
0#
#306
1#
b01110000 *
b010010111 ,
b011011111 -
#307
0#
#308
1#
b01110011 *
b010011000 ,
b011100000 -
#309
0#
#310
1#
b01110000 *
b010011001 ,
b011100001 -
#311
0#
#312
1#
b01110001 *
b010011010 ,
b011100010 -
#313
0#
#314
1#
b010011011 ,
b011100011 -
#315
0#
#316
1#
b01110011 *
b010011100 ,
b011100100 -
#317
0#
#318
1#
b01110001 *
b010011101 ,
b011100101 -
#319
0#
#320
1#
b010011110 ,
b011100110 -
#321
0#
#322
1#
b01101111 *
b010011111 ,
b011100111 -
#323
0#
#324
1#
b01110000 *
b010100000 ,
b011101000 -
#325
0#
#326
1#
b01101110 *
b010100001 ,
b011101001 -
#327
0#
#328
1#
b01101101 *
b010100010 ,
b011101010 -
#329
0#
#330
1#
b01101111 *
b010100011 ,
b011101011 -
#331
0#
#332
1#
b01101101 *
b010100100 ,
b011101100 -
#333
0#
#334
1#
b01110001 *
b010100101 ,
b011101101 -
#335
0#
#336
1#
b010100110 ,
b011101110 -
#337
0#
#338
1#
b01110000 *
b010100111 ,
b011101111 -
#339
0#
#340
1#
b01110001 *
b010101000 ,
b011110000 -
#341
0#
#342
1#
b01110000 *
b010101001 ,
b011110001 -
#343
0#
#344
1#
b01101111 *
b010101010 ,
b011110010 -
#345
0#
#346
1#
b01110000 *
b010101011 ,
b011110011 -
#347
0#
#348
1#
b01110010 *
b010101100 ,
b011110100 -
#349
0#
#350
1#
b01101111 *
b010101101 ,
b011110101 -
#351
0#
#352
1#
b01110000 *
b010101110 ,
b011110110 -
#353
0#
#354
1#
b01101011 *
b010101111 ,
b011110111 -
#355
0#
#356
1#
b01101101 *
b010110000 ,
b011111000 -
#357
0#
#358
1#
b010110001 ,
b011111001 -
#359
0#
#360
1#
b010110010 ,
b011111010 -
#361
0#
#362
1#
b01101111 *
b010110011 ,
b011111011 -
#363
0#
#364
1#
b01101101 *
b010110100 ,
b011111100 -
#365
0#
#366
1#
b01101110 *
b010110101 ,
b011111101 -
#367
0#
#368
1#
b01110000 *
b010110110 ,
b011111110 -
#369
0#
#370
1#
b010110111 ,
b011111111 -
#371
0#
#372
1#
b01101110 *
b010111000 ,
b100000000 -
#373
0#
#374
1#
b01110000 *
b010111001 ,
b100000001 -
#375
0#
#376
1#
b01101111 *
b010111010 ,
b100000010 -
#377
0#
#378
1#
b010111011 ,
b100000011 -
#379
0#
#380
1#
b01110000 *
b010111100 ,
b100000100 -
#381
0#
#382
1#
b010111101 ,
b100000101 -
#383
0#
#384
1#
b01101110 *
b010111110 ,
b100000110 -
#385
0#
#386
1#
b01110000 *
b010111111 ,
b100000111 -
#387
0#
#388
1#
b01101111 *
b011000000 ,
b100001000 -
#389
0#
#390
1#
b01110001 *
b011000001 ,
b100001001 -
#391
0#
#392
1#
b01110000 *
b011000010 ,
b100001010 -
#393
0#
#394
1#
b01101111 *
b011000011 ,
b100001011 -
#395
0#
#396
1#
b01110001 *
b011000100 ,
b100001100 -
#397
0#
#398
1#
b01110010 *
b011000101 ,
b100001101 -
#399
0#
#400
1#
b01101100 *
b011000110 ,
b100001110 -
#401
0#
#402
1#
b01110001 *
b011000111 ,
b100001111 -
#403
0#
#404
1#
b011001000 ,
b100010000 -
#405
0#
#406
1#
b011001001 ,
b100010001 -
#407
0#
#408
1#
b01110010 *
b011001010 ,
b100010010 -
#409
0#
#410
1#
b01101110 *
b011001011 ,
b100010011 -
#411
0#
#412
1#
b01110000 *
b011001100 ,
b100010100 -
#413
0#
#414
1#
b01101101 *
b011001101 ,
b100010101 -
#415
0#
#416
1#
b01101110 *
b011001110 ,
b100010110 -
#417
0#
#418
1#
b01101111 *
b011001111 ,
b100010111 -
#419
0#
#420
1#
b01101110 *
b011010000 ,
b100011000 -
#421
0#
#422
1#
b01101011 *
b011010001 ,
b100011001 -
#423
0#
#424
1#
b01101001 *
b011010010 ,
b100011010 -
#425
0#
#426
1#
b01101011 *
b011010011 ,
b100011011 -
#427
0#
#428
1#
b01101001 *
b011010100 ,
b100011100 -
#429
0#
#430
1#
b01101011 *
b011010101 ,
b100011101 -
#431
0#
#432
1#
b011010110 ,
b100011110 -
#433
0#
#434
1#
b01101101 *
b011010111 ,
b100011111 -
#435
0#
#436
1#
b01101010 *
b011011000 ,
b100100000 -
#437
0#
#438
1#
b01101001 *
b011011001 ,
b100100001 -
#439
0#
#440
1#
b01101010 *
b011011010 ,
b100100010 -
#441
0#
#442
1#
b011011011 ,
b100100011 -
#443
0#
#444
1#
b01101011 *
b011011100 ,
b100100100 -
#445
0#
#446
1#
b01101100 *
b011011101 ,
b100100101 -
#447
0#
#448
1#
b011011110 ,
b100100110 -
#449
0#
#450
1#
b01101011 *
b011011111 ,
b100100111 -
#451
0#
#452
1#
b01101110 *
b011100000 ,
b100101000 -
#453
0#
#454
1#
b01101101 *
b011100001 ,
b100101001 -
#455
0#
#456
1#
b01101110 *
b011100010 ,
b100101010 -
#457
0#
#458
1#
b01101100 *
b011100011 ,
b100101011 -
#459
0#
#460
1#
b01101001 *
b011100100 ,
b100101100 -
#461
0#
#462
1#
b011100101 ,
b100101101 -
#463
0#
#464
1#
b01101100 *
b011100110 ,
b100101110 -
#465
0#
#466
1#
b011100111 ,
b100101111 -
#467
0#
#468
1#
b01101110 *
b011101000 ,
b100110000 -
#469
0#
#470
1#
b011101001 ,
b100110001 -
#471
0#
#472
1#
b01101101 *
b011101010 ,
b100110010 -
#473
0#
#474
1#
b011101011 ,
b100110011 -
#475
0#
#476
1#
b01101011 *
b011101100 ,
b100110100 -
#477
0#
#478
1#
b01101100 *
b011101101 ,
b100110101 -
#479
0#
#480
1#
b01101011 *
b011101110 ,
b100110110 -
#481
0#
#482
1#
b01101101 *
b011101111 ,
b100110111 -
#483
0#
#484
1#
b011110000 ,
b100111000 -
#485
0#
#486
1#
b01101011 *
b011110001 ,
b100111001 -
#487
0#
#488
1#
b01101100 *
b011110010 ,
b100111010 -
#489
0#
#490
1#
b01101111 *
b011110011 ,
b100111011 -
#491
0#
#492
1#
b01101101 *
b011110100 ,
b100111100 -
#493
0#
#494
1#
b01101011 *
b011110101 ,
b100111101 -
#495
0#
#496
1#
b01101111 *
b011110110 ,
b100111110 -
#497
0#
#498
1#
b011110111 ,
b100111111 -
#499
0#
#500
1#
b011111000 ,
b101000000 -
#501
0#
#502
1#
b01101100 *
b011111001 ,
b101000001 -
#503
0#
#504
1#
b01101110 *
b011111010 ,
b101000010 -
#505
0#
#506
1#
b011111011 ,
b101000011 -
#507
0#
#508
1#
b01101101 *
b011111100 ,
b101000100 -
#509
0#
#510
1#
b011111101 ,
b101000101 -
#511
0#
#512
1#
b011111110 ,
b101000110 -
#513
0#
#514
1#
b01110000 *
b011111111 ,
b101000111 -
#515
0#
#516
1#
b01101111 *
b100000000 ,
b101001000 -
#517
0#
#518
1#
b01101101 *
b100000001 ,
b101001001 -
#519
0#
#520
1#
b01110000 *
b100000010 ,
b101001010 -
#521
0#
#522
1#
b01101110 *
b100000011 ,
b101001011 -
#523
0#
#524
1#
b100000100 ,
b101001100 -
#525
0#
#526
1#
b01101100 *
b100000101 ,
b101001101 -
#527
0#
#528
1#
b01101110 *
b100000110 ,
b101001110 -
#529
0#
#530
1#
b01101111 *
b100000111 ,
b101001111 -
#531
0#
#532
1#
b01101110 *
b100001000 ,
b101010000 -
#533
0#
#534
1#
b01101111 *
b100001001 ,
b101010001 -
#535
0#
#536
1#
b01101101 *
b100001010 ,
b101010010 -
#537
0#
#538
1#
b01110000 *
b100001011 ,
b101010011 -
#539
0#
#540
1#
b001000111 )
b100001100 ,
#541
0#
#542
1#
b001000110 )
b01101110 *
b100001101 ,
#543
0#
#544
1#
b100001110 ,
b101010100 -
#545
0#
#546
1#
b001000101 )
b01110010 *
b100001111 ,
#547
0#
#548
1#
b001000100 )
b01101011 *
b100010000 ,
#549
0#
#550
1#
b100010001 ,
b101010101 -
#551
0#
#552
1#
b001000011 )
b01101100 *
b100010010 ,
#553
0#
#554
1#
b001000010 )
b01100111 *
b100010011 ,
#555
0#
#556
1#
b01101010 *
b100010100 ,
b101010110 -
#557
0#
#558
1#
b001000001 )
b01101110 *
b100010101 ,
#559
0#
#560
1#
b01101001 *
b100010110 ,
b101010111 -
#561
0#
#562
1#
b01101110 *
b100010111 ,
b101011000 -
#563
0#
#564
1#
b01101101 *
b100011000 ,
b101011001 -
#565
0#
#566
1#
b01110000 *
b100011001 ,
b101011010 -
#567
0#
#568
1#
b100011010 ,
b101011011 -
#569
0#
#570
1#
b100011011 ,
b101011100 -
#571
0#
#572
1#
b01101111 *
b100011100 ,
b101011101 -
#573
0#
#574
1#
b01110000 *
b100011101 ,
b101011110 -
#575
0#
#576
1#
b100011110 ,
b101011111 -
#577
0#
#578
1#
b100011111 ,
b101100000 -
#579
0#
#580
1#
b100100000 ,
b101100001 -
#581
0#
#582
1#
b01101110 *
b100100001 ,
b101100010 -
#583
0#
#584
1#
b01110001 *
b100100010 ,
b101100011 -
#585
0#
#586
1#
b100100011 ,
b101100100 -
#587
0#
#588
1#
b100100100 ,
b101100101 -
#589
0#
#590
1#
b000111111 )
b100100101 ,
b101100100 -
#591
0#
#592
1#
b000111110 )
b01110000 *
b100100110 ,
#593
0#
#594
1#
b000111101 )
b100100111 ,
#595
0#
#596
1#
b01101111 *
b100101000 ,
b101100101 -
#597
0#
#598
1#
b000111100 )
b01101100 *
b100101001 ,
#599
0#
#600
1#
b000111011 )
b01101110 *
b100101010 ,
#601
0#
#602
1#
b100101011 ,
b101100110 -
#603
0#
#604
1#
b01101010 *
b100101100 ,
b101100111 -
#605
0#
#606
1#
b01101110 *
b100101101 ,
b101101000 -
#607
0#
#608
1#
b01101111 *
b100101110 ,
b101101001 -
#609
0#
#610
1#
b01101011 *
b100101111 ,
b101101010 -
#611
0#
#612
1#
b01101110 *
b100110000 ,
b101101011 -
#613
0#
#614
1#
b100110001 ,
b101101100 -
#615
0#
#616
1#
b01110000 *
b100110010 ,
b101101101 -
#617
0#
#618
1#
b01101111 *
b100110011 ,
b101101110 -
#619
0#
#620
1#
b01110001 *
b100110100 ,
b101101111 -
#621
0#
#622
1#
b01110000 *
b100110101 ,
b101110000 -
#623
0#
#624
1#
b01101110 *
b100110110 ,
b101110001 -
#625
0#
#626
1#
b01101101 *
b100110111 ,
b101110010 -
#627
0#
#628
1#
b01101100 *
b100111000 ,
b101110011 -
#629
0#
#630
1#
b000111010 )
b01110001 *
b100111001 ,
#631
0#
#632
1#
b000111001 )
b01101110 *
b100111010 ,
#633
0#
#634
1#
b000111000 )
b01101101 *
b100111011 ,
#635
0#
#636
1#
b000110111 )
b01101110 *
b100111100 ,
#637
0#
#638
1#
b000110110 )
b01101111 *
b100111101 ,
#639
0#
#640
1#
b01101110 *
b100111110 ,
b101110100 -
#641
0#
#642
1#
b01110000 *
b100111111 ,
b101110101 -
#643
0#
#644
1#
b000110101 )
b01110011 *
b101000000 ,
#645
0#
#646
1#
b101000001 ,
b101110110 -
#647
0#
#648
1#
b01110001 *
b101000010 ,
b101110111 -
#649
0#
#650
1#
b01101110 *
b101000011 ,
b101111000 -
#651
0#
#652
1#
b01110000 *
b101000100 ,
b101111001 -
#653
0#
#654
1#
b01101100 *
b101000101 ,
b101111010 -
#655
0#
#656
1#
b01101110 *
b101000110 ,
b101111011 -
#657
0#
#658
1#
b01101111 *
b101000111 ,
b101111100 -
#659
0#
#660
1#
b01101101 *
b101001000 ,
b101111101 -
#661
0#
#662
1#
b01101111 *
b101001001 ,
b101111110 -
#663
0#
#664
1#
b01101110 *
b101001010 ,
b101111111 -
#665
0#
#666
1#
b01101111 *
b101001011 ,
b110000000 -
#667
0#
#668
1#
b000110100 )
b01110001 *
b101001100 ,
#669
0#
#670
1#
b000110011 )
b01110000 *
b101001101 ,
#671
0#
#672
1#
b000110010 )
b01101101 *
b101001110 ,
#673
0#
#674
1#
b000110000 )
b101001111 ,
b101111111 -
#675
0#
#676
1#
b000101110 )
b01101111 *
b101010000 ,
b101111110 -
#677
0#
#678
1#
b101010001 ,
b101111111 -
#679
0#
#680
1#
b01101101 *
b101010010 ,
b110000000 -
#681
0#
#682
1#
b01101100 *
b101010011 ,
b110000001 -
#683
0#
#684
1#
b01101111 *
b101010100 ,
b110000010 -
#685
0#
#686
1#
b01101101 *
b101010101 ,
b110000011 -
#687
0#
#688
1#
b01101100 *
b101010110 ,
b110000100 -
#689
0#
#690
1#
b101010111 ,
b110000101 -
#691
0#
#692
1#
b01101110 *
b101011000 ,
b110000110 -
#693
0#
#694
1#
b01110001 *
b101011001 ,
b110000111 -
#695
0#
#696
1#
b01110000 *
b101011010 ,
b110001000 -
#697
0#
#698
1#
b01101110 *
b101011011 ,
b110001001 -
#699
0#
#700
1#
b01101100 *
b101011100 ,
b110001010 -
#701
0#
#702
1#
b01101110 *
b101011101 ,
b110001011 -
#703
0#
#704
1#
b01101101 *
b101011110 ,
b110001100 -
#705
0#
#706
1#
b01110000 *
b101011111 ,
b110001101 -
#707
0#
#708
1#
b101100000 ,
b110001110 -
#709
0#
#710
1#
b000101100 )
b01101111 *
b101100001 ,
b110001101 -
#711
0#
#712
1#
b000101010 )
b01101100 *
b101100010 ,
b110001100 -
#713
0#
#714
1#
b000101001 )
b101100011 ,
#715
0#
#716
1#
b000101000 )
b01110000 *
b101100100 ,
#717
0#
#718
1#
b01101101 *
b101100101 ,
b110001101 -
#719
0#
#720
1#
b01101100 *
b101100110 ,
b110001110 -
#721
0#
#722
1#
b01101101 *
b101100111 ,
b110001111 -
#723
0#
#724
1#
b101101000 ,
b110010000 -
#725
0#
#726
1#
b01101011 *
b101101001 ,
b110010001 -
#727
0#
#728
1#
b01101110 *
b101101010 ,
b110010010 -
#729
0#
#730
1#
b01101111 *
b101101011 ,
b110010011 -
#731
0#
#732
1#
b01101110 *
b101101100 ,
b110010100 -
#733
0#
#734
1#
b01110000 *
b101101101 ,
b110010101 -
#735
0#
#736
1#
b101101110 ,
b110010110 -
#737
0#
#738
1#
b01101001 *
b101101111 ,
b110010111 -
#739
0#
#740
1#
b01101100 *
b101110000 ,
b110011000 -
#741
0#
#742
1#
b101110001 ,
b110011001 -
#743
0#
#744
1#
b01101110 *
b101110010 ,
b110011010 -
#745
0#
#746
1#
b01101100 *
b101110011 ,
b110011011 -
#747
0#
#748
1#
b000100111 )
b01101110 *
b101110100 ,
#749
0#
#750
1#
b000100110 )
b01110001 *
b101110101 ,
#751
0#
#752
1#
b000100101 )
b01101101 *
b101110110 ,
#753
0#
#754
1#
b000100100 )
b101110111 ,
#755
0#
#756
1#
b000100011 )
b01101110 *
b101111000 ,
#757
0#
#758
1#
b01101111 *
b101111001 ,
b110011100 -
#759
0#
#760
1#
b101111010 ,
b110011101 -
#761
0#
#762
1#
b01101101 *
b101111011 ,
b110011110 -
#763
0#
#764
1#
b01110001 *
b101111100 ,
b110011111 -
#765
0#
#766
1#
b01101110 *
b101111101 ,
b110100000 -
#767
0#
#768
1#
b01110000 *
b101111110 ,
b110100001 -
#769
0#
#770
1#
b01101111 *
b101111111 ,
b110100010 -
#771
0#
#772
1#
b01110001 *
b110000000 ,
b110100011 -
#773
0#
#774
1#
b01101110 *
b110000001 ,
b110100100 -
#775
0#
#776
1#
b110000010 ,
b110100101 -
#777
0#
#778
1#
b110000011 ,
b110100110 -
#779
0#
#780
1#
b110000100 ,
b110100111 -
#781
0#
#782
1#
b110000101 ,
b110101000 -
#783
0#
#784
1#
b110000110 ,
b110101001 -
#785
0#
#786
1#
b01101111 *
b110000111 ,
b110101010 -
#787
0#
#788
1#
b01101110 *
b110001000 ,
b110101011 -
#789
0#
#790
1#
b000100010 )
b01101111 *
b110001001 ,
#791
0#
#792
1#
b000100001 )
b01101101 *
b110001010 ,
#793
0#
#794
1#
b000011111 )
b01101110 *
b110001011 ,
b110101010 -
#795
0#
